odoo10_addon_product_supplierinfo_for_customer_sale-10.0.1.0.1-py3.8-nspkg.pth
odoo/addons/product_supplierinfo_for_customer_sale/README.rst
odoo/addons/product_supplierinfo_for_customer_sale/__init__.py
odoo/addons/product_supplierinfo_for_customer_sale/__manifest__.py
odoo/addons/product_supplierinfo_for_customer_sale/i18n/ca.po
odoo/addons/product_supplierinfo_for_customer_sale/i18n/de.po
odoo/addons/product_supplierinfo_for_customer_sale/i18n/es.po
odoo/addons/product_supplierinfo_for_customer_sale/i18n/it.po
odoo/addons/product_supplierinfo_for_customer_sale/i18n/product_supplierinfo_for_customer_sale.pot
odoo/addons/product_supplierinfo_for_customer_sale/models/__init__.py
odoo/addons/product_supplierinfo_for_customer_sale/models/sale.py
odoo/addons/product_supplierinfo_for_customer_sale/static/description/icon.png
odoo/addons/product_supplierinfo_for_customer_sale/tests/__init__.py
odoo/addons/product_supplierinfo_for_customer_sale/tests/test_product_supplierinfo_for_customer_sale.py
odoo/addons/product_supplierinfo_for_customer_sale/views/sale_view.xml
odoo10_addon_product_supplierinfo_for_customer_sale-10.0.1.0.1.dist-info/METADATA
odoo10_addon_product_supplierinfo_for_customer_sale-10.0.1.0.1.dist-info/WHEEL
odoo10_addon_product_supplierinfo_for_customer_sale-10.0.1.0.1.dist-info/namespace_packages.txt
odoo10_addon_product_supplierinfo_for_customer_sale-10.0.1.0.1.dist-info/top_level.txt
odoo10_addon_product_supplierinfo_for_customer_sale-10.0.1.0.1.dist-info/RECORD
